setup.py
dsnd_distributions_package/Binomialdistribution.py
dsnd_distributions_package/Gaussiandistribution.py
dsnd_distributions_package/Generaldistribution.py
dsnd_distributions_package/__init__.py
dsnd_distributions_package.egg-info/PKG-INFO
dsnd_distributions_package.egg-info/SOURCES.txt
dsnd_distributions_package.egg-info/dependency_links.txt
dsnd_distributions_package.egg-info/not-zip-safe
dsnd_distributions_package.egg-info/top_level.txt