Metadata-Version: 1.0
Name: dsnd-distributions-package
Version: 0.1
Summary: Gaussian and Binomial distributions
Home-page: UNKNOWN
Author: Slade McKee
Author-email: slade.mckee@gmail.com
License: UNKNOWN
Platform: UNKNOWN
